pypgconfig/__init__.py
PyPgConfig-0.1.0a2.dist-info/LICENSE
PyPgConfig-0.1.0a2.dist-info/METADATA
PyPgConfig-0.1.0a2.dist-info/WHEEL
PyPgConfig-0.1.0a2.dist-info/top_level.txt
PyPgConfig-0.1.0a2.dist-info/RECORD
