Metadata-Version: 2.1
Name: PyPgConfig
Version: 0.1.0a2
Summary: Access pg_config from Python
Home-page: https://github.com/Florents-Tselai/PyPgConfig
Author: Florents Tselai
Author-email: florents@tselai.com
License: Apache License, Version 2.0
Project-URL: Documentation, https://github.com/Florents-Tselai/PyPgConfig
Project-URL: Issues, https://github.com/Florents-Tselai/PyPgConfig/issues
Project-URL: CI, https://github.com/Florents-Tselai/PyPgConfig/actions
Project-URL: Changelog, https://github.com/Florents-Tselai/PyPgConfig/releases
Requires-Python: >=3.7
License-File: LICENSE
Requires-Dist: setuptools
Requires-Dist: pip
Provides-Extra: test
Requires-Dist: pytest ; extra == 'test'
Requires-Dist: pytest-cov ; extra == 'test'
Requires-Dist: black ; extra == 'test'
Requires-Dist: ruff ; extra == 'test'
